jubeatools/__init__.py
jubeatools/cli/__init__.py
jubeatools/cli/cli.py
jubeatools/cli/helpers.py
jubeatools/cli/tests/__init__.py
jubeatools/cli/tests/data/Life Without You.eve
jubeatools/cli/tests/data/__init__.py
jubeatools/cli/tests/data/memon_merge/Sky Bus For Hire ADV.memon
jubeatools/cli/tests/data/memon_merge/Sky Bus For Hire BSC.memon
jubeatools/cli/tests/data/memon_merge/Sky Bus For Hire EXT.memon
jubeatools/cli/tests/test_cli.py
jubeatools/conftest.py
jubeatools/formats/__init__.py
jubeatools/formats/dump_tools.py
jubeatools/formats/filetypes.py
jubeatools/formats/format_names.py
jubeatools/formats/guess.py
jubeatools/formats/jubeat_analyser/__init__.py
jubeatools/formats/jubeat_analyser/command.py
jubeatools/formats/jubeat_analyser/dump_tools.py
jubeatools/formats/jubeat_analyser/load_tools.py
jubeatools/formats/jubeat_analyser/memo/__init__.py
jubeatools/formats/jubeat_analyser/memo/dump.py
jubeatools/formats/jubeat_analyser/memo/load.py
jubeatools/formats/jubeat_analyser/memo1/__init__.py
jubeatools/formats/jubeat_analyser/memo1/dump.py
jubeatools/formats/jubeat_analyser/memo1/load.py
jubeatools/formats/jubeat_analyser/memo2/__init__.py
jubeatools/formats/jubeat_analyser/memo2/dump.py
jubeatools/formats/jubeat_analyser/memo2/dump_iboogie.py
jubeatools/formats/jubeat_analyser/memo2/load.py
jubeatools/formats/jubeat_analyser/memo2/load_iboogie.py
jubeatools/formats/jubeat_analyser/mono_column/__init__.py
jubeatools/formats/jubeat_analyser/mono_column/dump.py
jubeatools/formats/jubeat_analyser/mono_column/load.py
jubeatools/formats/jubeat_analyser/symbol_definition.py
jubeatools/formats/jubeat_analyser/symbols.py
jubeatools/formats/jubeat_analyser/tests/__init__.py
jubeatools/formats/jubeat_analyser/tests/data/Booths_of_Fighters_memo.txt
jubeatools/formats/jubeat_analyser/tests/data/MTC_Mimi_EXT.txt
jubeatools/formats/jubeat_analyser/tests/data/MTC_Nageki_no_Ki_EXT.txt
jubeatools/formats/jubeat_analyser/tests/data/RorataJin's example.txt
jubeatools-3.0.0.dist-info/METADATA
jubeatools-3.0.0.dist-info/WHEEL
jubeatools-3.0.0.dist-info/entry_points.txt
jubeatools-3.0.0.dist-info/RECORD
