Metadata-Version: 2.1
Name: jubeatools
Version: 3.0.0
Summary: A toolbox for jubeat file formats
Home-page: https://gitlab.com/square-game-liberation-front/jubeatools
Author: Stepland
Author-email: 10530295-Buggyroom@users.noreply.gitlab.com
Requires-Python: >=3.9,<4.0
Classifier: Programming Language :: Python :: 3
Classifier: Programming Language :: Python :: 3.9
Classifier: Programming Language :: Python :: 3.10
Classifier: Programming Language :: Python :: 3.11
Classifier: Programming Language :: Python :: 3.12
Requires-Dist: click (>=8.0.3,<9.0.0)
Requires-Dist: construct (>=2.10,<3.0)
Requires-Dist: construct-typing (>=0.5.3,<0.6.0)
Requires-Dist: marshmallow (>=3.6.0,<4.0.0)
Requires-Dist: marshmallow-dataclass[enum,union] (>=8.5.14,<9.0.0)
Requires-Dist: more-itertools (>=8.4.0,<9.0.0)
Requires-Dist: parsimonious (>=0.10.0,<0.11.0)
Requires-Dist: python-constraint (>=1.4.0,<2.0.0)
Requires-Dist: simplejson (>=3.17.0,<4.0.0)
Requires-Dist: sortedcontainers (>=2.3.0,<3.0.0)
Project-URL: Documentation, https://jubeatools.readthedocs.io/en/latest/
Project-URL: Repository, https://gitlab.com/square-game-liberation-front/jubeatools
